{
  "db_name": "SQLite",
  "query": "SELECT keywords as \"keywords!\", created_at as \"created_at!\"\n         FROM memory_fragments WHERE creator_id = ?",
  "describe": {
    "columns": [
      {
        "name": "keywords!",
        "ordinal": 0,
        "type_info": "Text"
      },
      {
        "name": "created_at!",
        "ordinal": 1,
        "type_info": "Text"
      }
    ],
    "parameters": {
      "Right": 1
    },
    "nullable": [
      false,
      false
    ]
  },
  "hash": "f70ab5c17931ad068bd50043bd25dd698fd8f294fee7715f3c005f9482ad57a9"
}
