{
  "db_name": "SQLite",
  "query": "INSERT INTO kb_relationships\n           (relationship_id, world_id, source_entity_id, target_entity_id,\n            relation_type, custom_label, symmetric, confidence,\n            source_anchor_ids, metadata, created_at, updated_at, revision)\n           VALUES (?, ?, ?, ?, ?, ?, ?, ?, ?, ?, ?, ?, ?)",
  "describe": {
    "columns": [],
    "parameters": {
      "Right": 13
    },
    "nullable": []
  },
  "hash": "5b3c86ddcccb8c82b1fc22b61da15bfd73908116805d7c84685e164e43d3e85a"
}
